MANIFEST.in
README.rst
VERSION
setup.cfg
setup.py
direg/__init__.py
direg/main.py
direg.egg-info/PKG-INFO
direg.egg-info/SOURCES.txt
direg.egg-info/dependency_links.txt
direg.egg-info/top_level.txt
test/test_namespaces.py
test/_data/registry.py
test/_packages/one.py