Metadata-Version: 1.1
Name: direg
Version: 0.2.6
Summary: A drop-in registry. Easily maintain a central configuration registry for your complex python project.
Home-page: https://github.com/stnbu/direg
Author: Mike Burr
Author-email: mburr@unintuitive.org
License: MIT
Download-URL: https://github.com/stnbu/direg/archive/master.zip
Keywords: configuration,registry,refactor
Platform: UNKNOWN
Classifier: Development Status :: 4 - Beta
Classifier: Intended Audience :: Developers
Classifier: License :: OSI Approved :: MIT License
Classifier: Programming Language :: Python :: 2
Classifier: Topic :: Software Development
Classifier: Topic :: Utilities
Provides: direg
